perceptionml-0.1.0.dist-info/licenses/LICENSE
pipeline/__init__.py
pipeline/auto_config.py
pipeline/auto_parameters.py
pipeline/cli.py
pipeline/clustering.py
pipeline/code_reference_finder.py
pipeline/config.py
pipeline/data_exporter.py
pipeline/data_exporter_readme.py
pipeline/data_exporter_readme_v2.py
pipeline/data_loader.py
pipeline/dimensionality.py
pipeline/dml_analysis.py
pipeline/embeddings.py
pipeline/visualization.py
pipeline/configs/anger_zero_presence.yaml
pipeline/configs/default.yaml
pipeline/configs/essay_analysis.yaml
pipeline/configs/essay_analysis_adjusted.yaml
pipeline/templates/base.html.j2
pipeline/templates/components/controls.html.j2
pipeline/templates/components/dml_table.html.j2
pipeline/templates/components/gallery_controls.html.j2
pipeline/templates/components/pc_global_info.html.j2
pipeline/templates/components/text_display.html.j2
pipeline/templates/components/topic_stats.html.j2
pipeline/templates/js/dml_stats.js.j2
pipeline/templates/js/interactions.js.j2
pipeline/templates/js/pca_stats.js.j2
pipeline/templates/js/topic_stats.js.j2
pipeline/templates/js/visualization.js.j2
perceptionml-0.1.0.dist-info/METADATA
perceptionml-0.1.0.dist-info/WHEEL
perceptionml-0.1.0.dist-info/entry_points.txt
perceptionml-0.1.0.dist-info/top_level.txt
perceptionml-0.1.0.dist-info/RECORD
