Metadata-Version: 2.4
Name: perceptionml
Version: 0.1.0
Summary: A text embedding analysis pipeline for perception modeling
Author-email: "Raymond V. Li" <raymond@raymondli.me>
License: Apache-2.0
Project-URL: Homepage, https://github.com/raymondli/perceptionml
Project-URL: Bug Tracker, https://github.com/raymondli/perceptionml/issues
Classifier: Development Status :: 3 - Alpha
Classifier: Intended Audience :: Science/Research
Classifier: Programming Language :: Python :: 3
Classifier: Programming Language :: Python :: 3.8
Classifier: Programming Language :: Python :: 3.9
Classifier: Programming Language :: Python :: 3.10
Classifier: Programming Language :: Python :: 3.11
Requires-Python: >=3.8
License-File: LICENSE
Requires-Dist: numpy==1.26.4
Requires-Dist: pandas==2.2.3
Requires-Dist: scipy==1.15.3
Requires-Dist: scikit-learn==1.5.2
Requires-Dist: statsmodels==0.14.4
Requires-Dist: torch==2.6.0
Requires-Dist: torchaudio==2.6.0
Requires-Dist: torchvision==0.21.0
Requires-Dist: transformers==4.42.4
Requires-Dist: sentence-transformers==4.1.0
Requires-Dist: accelerate==1.7.0
Requires-Dist: safetensors==0.5.3
Requires-Dist: tokenizers==0.19.1
Requires-Dist: huggingface-hub==0.32.2
Requires-Dist: datasets==3.6.0
Requires-Dist: einops==0.8.1
Requires-Dist: umap-learn==0.5.7
Requires-Dist: hdbscan==0.8.40
Requires-Dist: xgboost==3.0.1
Requires-Dist: shap==0.43.0
Requires-Dist: matplotlib==3.10.3
Requires-Dist: seaborn==0.13.2
Requires-Dist: jinja2==3.1.6
Requires-Dist: pyyaml==6.0.2
Requires-Dist: click==8.1.8
Requires-Dist: tqdm==4.67.1
Dynamic: license-file
